simple_telegram_api/__init__.py
simple_telegram_api/exceptions.py
simple_telegram_api/main.py
simple_telegram_api-1.0.1.dist-info/licenses/LICENSE
simple_telegram_api-1.0.1.dist-info/METADATA
simple_telegram_api-1.0.1.dist-info/WHEEL
simple_telegram_api-1.0.1.dist-info/top_level.txt
simple_telegram_api-1.0.1.dist-info/RECORD
