Metadata-Version: 2.4
Name: simple-telegram-api
Version: 1.0.1
Summary: A simple and easy-to-use Python wrapper for Telegram bots.
Author-email: Ahmet Burhan Kayalı <ahmetburhan1703@gmail.com>
License-Expression: MIT
Project-URL: Homepage, https://github.com/SoAp9035/simple-telegram-api
Project-URL: Bug Tracker, https://github.com/SoAp9035/simple-telegram-api/issues
Keywords: simple,telegram,bot,api,wrapper
Classifier: Intended Audience :: Developers
Classifier: Intended Audience :: Science/Research
Classifier: Topic :: Software Development :: Libraries :: Python Modules
Classifier: Topic :: Internet :: WWW/HTTP
Requires-Python: >=3.10
License-File: LICENSE
Requires-Dist: requests==2.32.5
Dynamic: license-file
